apollo_modules/__init__.py
apollo_modules/modules/__init__.py
apollo_modules/modules/audio/__init__.py
apollo_modules/modules/audio/proto/__init__.py
apollo_modules/modules/audio/proto/audio_conf_pb2.py
apollo_modules/modules/bridge/__init__.py
apollo_modules/modules/bridge/proto/__init__.py
apollo_modules/modules/bridge/proto/udp_bridge_remote_info_pb2.py
apollo_modules/modules/canbus/__init__.py
apollo_modules/modules/canbus/proto/__init__.py
apollo_modules/modules/canbus/proto/canbus_conf_pb2.py
apollo_modules/modules/canbus/proto/vehicle_parameter_pb2.py
apollo_modules/modules/canbus_vehicle/__init__.py
apollo_modules/modules/canbus_vehicle/ch/__init__.py
apollo_modules/modules/canbus_vehicle/ch/proto/__init__.py
apollo_modules/modules/canbus_vehicle/ch/proto/ch_pb2.py
apollo_modules/modules/canbus_vehicle/devkit/__init__.py
apollo_modules/modules/canbus_vehicle/devkit/proto/__init__.py
apollo_modules/modules/canbus_vehicle/devkit/proto/devkit_pb2.py
apollo_modules/modules/canbus_vehicle/ge3/__init__.py
apollo_modules/modules/canbus_vehicle/ge3/proto/__init__.py
apollo_modules/modules/canbus_vehicle/ge3/proto/ge3_pb2.py
apollo_modules/modules/canbus_vehicle/gem/__init__.py
apollo_modules/modules/canbus_vehicle/gem/proto/__init__.py
apollo_modules/modules/canbus_vehicle/gem/proto/gem_pb2.py
apollo_modules/modules/canbus_vehicle/lexus/__init__.py
apollo_modules/modules/canbus_vehicle/lexus/proto/__init__.py
apollo_modules/modules/canbus_vehicle/lexus/proto/lexus_pb2.py
apollo_modules/modules/canbus_vehicle/lincoln/__init__.py
apollo_modules/modules/canbus_vehicle/lincoln/proto/__init__.py
apollo_modules/modules/canbus_vehicle/lincoln/proto/lincoln_pb2.py
apollo_modules/modules/canbus_vehicle/neolix_edu/__init__.py
apollo_modules/modules/canbus_vehicle/neolix_edu/proto/__init__.py
apollo_modules/modules/canbus_vehicle/neolix_edu/proto/neolix_edu_pb2.py
apollo_modules/modules/canbus_vehicle/transit/__init__.py
apollo_modules-9.0.2.dist-info/METADATA
apollo_modules-9.0.2.dist-info/WHEEL
apollo_modules-9.0.2.dist-info/top_level.txt
apollo_modules-9.0.2.dist-info/RECORD
