Metadata-Version: 2.1
Name: apollo_modules
Version: 9.0.2
Summary: This is a package including baidu apollo' proto modules
Home-page: https://github.com/MingfeiCheng/ApolloPyProto
Author: MingfeiCheng
Author-email: snowbirds.mf@gmail.com
Classifier: Programming Language :: Python :: 3
Classifier: License :: OSI Approved :: MIT License
Classifier: Operating System :: OS Independent
Requires-Python: >=3.6
Requires-Dist: protobuf ==3.20.1
